gpugrab/__init__.py
gpugrab/get_idle.py
gpugrab/gpuinfo.py
gpugrab-0.1.0.dist-info/METADATA
gpugrab-0.1.0.dist-info/WHEEL
gpugrab-0.1.0.dist-info/top_level.txt
gpugrab-0.1.0.dist-info/RECORD
